{"metadata":{"title":"Page not found – RSG","robots":"noindex, nofollow","generator":["WordPress 6.9","Elementor 3.33.5; features: e_font_icon_svg, additional_custom_breakpoints; settings: css_print_method-external, google_font-enabled, font_display-swap"],"position":["1","2"],"msapplication-TileImage":"https://rsgprofilesheets.com/wp-content/uploads/2025/11/cropped-cropped-RSG-Site-Icon-270x270.png","language":"en-US","viewport":"width=device-width, initial-scale=1","favicon":"https://rsgprofilesheets.com/wp-content/uploads/2025/11/cropped-cropped-RSG-Site-Icon-32x32.png","scrapeId":"019ee860-655f-76ce-871a-32d06dd17aba","sourceURL":"https://rsgprofilesheets.com/colour-coated-roofing-sheets/","url":"https://rsgprofilesheets.com/colour-coated-roofing-sheets/","statusCode":404,"error":"Not Found","contentType":"text/html; charset=UTF-8","timezone":"America/New_York","proxyUsed":"basic","cacheState":"miss","indexId":"7324a2b2-c7d4-4fa8-8ee7-614e9e69a1fe","creditsUsed":1,"concurrencyLimited":false},"html":"<!DOCTYPE html><html lang=\"en-US\">\n\n<body class=\"error404 wp-embed-responsive wp-theme-roofx wp-child-theme-roofx-child ehf-footer ehf-template-roofx ehf-stylesheet-roofx-child hfeed no-sidebar elementor-default elementor-kit-20 e--ua-blink e--ua-chrome e--ua-webkit\" data-elementor-device-mode=\"none\" style=\"\">\n\n    \n\n    \n\n            <!--Preloader-->\n        <div id=\"preloader\" style=\"display: none;\">\n            <div class=\"ta-preloader-block\">\n                <div class=\"ta-spinner-eff\">\n                    <div class=\"ta-bar ta-bar-top\"></div>\n                    <div class=\"ta-bar ta-bar-right\"></div>\n                    <div class=\"ta-bar ta-bar-bottom\"></div>\n                    <div class=\"ta-bar ta-bar-left\"></div>\n                </div>\n            </div>\n        </div>\n        <!--Preloader-end -->\n    \n\n            <!-- Scroll-top -->\n        <button class=\"scroll-top scroll-to-target\" data-target=\"html\">\n            <i class=\"fas fa-level-up-alt\"></i>\n        </button>\n        <!-- Scroll-top-end-->\n    \n\n    \n<!-- header-area -->\n<header>\n    <div id=\"header-fixed-height\" class=\"\"></div>\n\n            <div class=\"header-top-wrap\">\n            <div class=\"container\">\n                <div class=\"row justify-content-center\">\n                                            <div class=\"col-xl-8 col-lg-9\">\n                            <div class=\"header-top-left\">\n                                <ul class=\"list-wrap\">\n                                                                            <li>Welcome to RSG Profile</li>\n                                    \n                                                                            <li><i class=\"fas fa-phone-alt\"></i><a href=\"tel:+91 99185 22988\">+91 99185 22988</a></li>\n                                    \n                                                                            <li><i class=\"fas fa-envelope\"></i><a href=\"mailto:shivam.gupta09@gmail.com\">shivam.gupta09@gmail.com</a></li>\n                                                                    </ul>\n                            </div>\n                        </div>\n                    \n                                            <div class=\"col-xl-4 col-lg-3\">\n                            <div class=\"header-top-right\">\n\n                                                                    <div class=\"header-lang\">\n                                        <div class=\"dropdown\">\n                                            <button class=\"dropdown-toggle\" type=\"button\" id=\"dropdownMenuButton1\" data-bs-toggle=\"dropdown\" aria-haspopup=\"true\" aria-expanded=\"false\">\n                                                🇺🇸 English                                            </button>\n                                            <div class=\"dropdown-menu\" aria-labelledby=\"dropdownMenuButton1\"><a href=\"https://rsgprofilesheets.com/colour-coated-roofing-sheets/#\" class=\"dropdown-item\">🇷🇺 Russia</a><a href=\"https://rsgprofilesheets.com/colour-coated-roofing-sheets/#\" class=\"dropdown-item\">🇮🇳 India</a><a href=\"https://rsgprofilesheets.com/colour-coated-roofing-sheets/#\" class=\"dropdown-item\">🇹🇷 Turkey</a><a href=\"https://rsgprofilesheets.com/colour-coated-roofing-sheets/#\" class=\"dropdown-item\">🇫🇷 France</a> </div>                                        </div>\n                                    </div>\n                                \n                                                                    <div class=\"header-social\">\n                                        <ul class=\"list-wrap\">\n\n                                                                                            <li><a href=\"https://rsgprofilesheets.com/colour-coated-roofing-sheets/#\"><i class=\"fab fa-facebook-f\"></i></a></li>\n                                            \n                                                                                            <li><a href=\"https://www.linkedin.com/company/rsg-profile-manufacturing-private-limited/\"><i class=\"fab fa-linkedin-in\"></i></a></li>\n                                            \n                                                                                            <li><a href=\"https://rsgprofilesheets.com/colour-coated-roofing-sheets/#\"><i class=\"fab fa-twitter\"></i></a></li>\n                                            \n                                                                                            <li><a href=\"https://rsgprofilesheets.com/colour-coated-roofing-sheets/#\"><i class=\"fab fa-youtube\"></i></a></li>\n                                            \n                                        </ul>\n                                    </div>\n                                                            </div>\n                        </div>\n                                    </div>\n            </div>\n        </div>\n    \n    <div id=\"sticky-header\" class=\"menu-area menu-area-three roofx-menu-has-showing\">\n        <div class=\"container\">\n            <div class=\"row\">\n                <div class=\"col-12\">\n                                            <div class=\"mobile-nav-toggler\"><i class=\"fas fa-bars\"></i></div>\n                                        <div class=\"menu-wrap\">\n                        <nav class=\"menu-nav\">\n                            <div class=\"logo\">\n                                      \n               <a class=\"main-logo\" href=\"https://rsgprofilesheets.com/\">\n             <img src=\"https://rsgprofilesheets.com/wp-content/uploads/2024/09/rsg-logo.png\" style=\"max-height: 80px\" alt=\"Logo\">\n         </a>\n                                     </div>\n                            <div class=\"navbar-wrap main-menu d-none d-lg-flex\">\n                                    <ul id=\"menu-global-menu\" class=\"navigation\"><li itemscope=\"itemscope\" itemtype=\"https://www.schema.org/SiteNavigationElement\" id=\"menu-item-1495\" class=\"menu-item menu-item-type-post_type menu-item-object-page menu-item-home menu-item-1495 nav-item\"><a title=\"Home\" href=\"https://rsgprofilesheets.com/\" class=\"nav-links\">Home</a></li>\n<li itemscope=\"itemscope\" itemtype=\"https://www.schema.org/SiteNavigationElement\" id=\"menu-item-1494\" class=\"menu-item menu-item-type-post_type menu-item-object-page menu-item-1494 nav-item\"><a title=\"About Us\" href=\"https://rsgprofilesheets.com/about-us-2/\" class=\"nav-links\">About Us</a></li>\n<li itemscope=\"itemscope\" itemtype=\"https://www.schema.org/SiteNavigationElement\" id=\"menu-item-1547\" class=\"menu-item menu-item-type-post_type menu-item-object-page menu-item-has-children dropdown has-dropdown menu-item-1547 nav-item\"><a title=\"Products\" href=\"https://rsgprofilesheets.com/products/\" class=\"nav-links\">Products</a>\n<ul class=\"sub-menu\" role=\"menu\">\n\t<li itemscope=\"itemscope\" itemtype=\"https://www.schema.org/SiteNavigationElement\" id=\"menu-item-2888\" class=\"menu-item menu-item-type-custom menu-item-object-custom menu-item-has-children dropdown has-dropdown menu-item-2888 nav-item\"><a title=\"Colour Coated Roofing Sheet\" href=\"https://rsgprofilesheets.com/colour-coated-roofing-sheets/#\" class=\"dropdown-items\">Colour Coated Roofing Sheet</a>\n\t<ul class=\"sub-menu\" role=\"menu\">\n\t\t<li itemscope=\"itemscope\" itemtype=\"https://www.schema.org/SiteNavigationElement\" id=\"menu-item-2889\" class=\"menu-item menu-item-type-custom menu-item-object-custom menu-item-has-children dropdown has-dropdown menu-item-2889 nav-item\"><a title=\"PPGL\" href=\"https://rsgprofilesheets.com/colour-coated-roofing-sheets/#\" class=\"dropdown-items\">PPGL</a>\n\t\t<ul class=\"sub-menu\" role=\"menu\">\n\t\t\t<li itemscope=\"itemscope\" itemtype=\"https://www.schema.org/SiteNavigationElement\" id=\"menu-item-2565\" class=\"menu-item menu-item-type-post_type menu-item-object-page menu-item-2565 nav-item\"><a title=\"JSW Colouron+\" href=\"https://rsgprofilesheets.com/jsw-colouron/\" class=\"dropdown-items\">JSW Colouron+</a></li>\n\t\t\t<li itemscope=\"itemscope\" itemtype=\"https://www.schema.org/SiteNavigationElement\" id=\"menu-item-2567\" class=\"menu-item menu-item-type-post_type menu-item-object-page menu-item-2567 nav-item\"><a title=\"JSW Silveron+\" href=\"https://rsgprofilesheets.com/jsw-silveron/\" class=\"dropdown-items\">JSW Silveron+</a></li>\n\t\t\t<li itemscope=\"itemscope\" itemtype=\"https://www.schema.org/SiteNavigationElement\" id=\"menu-item-2566\" class=\"menu-item menu-item-type-post_type menu-item-object-page menu-item-2566 nav-item\"><a title=\"JSW Pragati+\" href=\"https://rsgprofilesheets.com/jsw-pragati/\" class=\"dropdown-items\">JSW Pragati+</a></li>\n\t\t\t<li itemscope=\"itemscope\" itemtype=\"https://www.schema.org/SiteNavigationElement\" id=\"menu-item-3085\" class=\"menu-item menu-item-type-post_type menu-item-object-page menu-item-3085 nav-item\"><a title=\"JSW Endura\" href=\"https://rsgprofilesheets.com/jsw-endura/\" class=\"dropdown-items\">JSW Endura</a></li>\n\t\t\t<li itemscope=\"itemscope\" itemtype=\"https://www.schema.org/SiteNavigationElement\" id=\"menu-item-2571\" class=\"menu-item menu-item-type-post_type menu-item-object-page menu-item-2571 nav-item\"><a title=\"Tata Durashine\" href=\"https://rsgprofilesheets.com/tata-durashine/\" class=\"dropdown-items\">Tata Durashine</a></li>\n\t\t\t<li itemscope=\"itemscope\" itemtype=\"https://www.schema.org/SiteNavigationElement\" id=\"menu-item-2564\" class=\"menu-item menu-item-type-post_type menu-item-object-page menu-item-2564 nav-item\"><a title=\"JINDAL India Sabrang\" href=\"https://rsgprofilesheets.com/jindal-sabrang/\" class=\"dropdown-items\">JINDAL India Sabrang</a></li>\n\t\t</ul>\n<div class=\"dropdown-btn\"><span class=\"fas fa-angle-down\"></span></div></li>\n\t\t<li itemscope=\"itemscope\" itemtype=\"https://www.schema.org/SiteNavigationElement\" id=\"menu-item-2890\" class=\"menu-item menu-item-type-custom menu-item-object-custom menu-item-has-children dropdown has-dropdown menu-item-2890 nav-item\"><a title=\"PPGI\" href=\"https://rsgprofilesheets.com/colour-coated-roofing-sheets/#\" class=\"dropdown-items\">PPGI</a>\n\t\t<ul class=\"sub-menu\" role=\"menu\">\n\t\t\t<li itemscope=\"itemscope\" itemtype=\"https://www.schema.org/SiteNavigationElement\" id=\"menu-item-2562\" class=\"menu-item menu-item-type-post_type menu-item-object-page menu-item-2562 nav-item\"><a title=\"Dura Glow\" href=\"https://rsgprofilesheets.com/dura-glow/\" class=\"dropdown-items\">Dura Glow</a></li>\n\t\t\t<li itemscope=\"itemscope\" itemtype=\"https://www.schema.org/SiteNavigationElement\" id=\"menu-item-2558\" class=\"menu-item menu-item-type-post_type menu-item-object-page menu-item-2558 nav-item\"><a title=\"AM/NS\" href=\"https://rsgprofilesheets.com/am-ns/\" class=\"dropdown-items\">AM/NS</a></li>\n\t\t</ul>\n<div class=\"dropdown-btn\"><span class=\"fas fa-angle-down\"></span></div></li>\n\t\t<li itemscope=\"itemscope\" itemtype=\"https://www.schema.org/SiteNavigationElement\" id=\"menu-item-2784\" class=\"menu-item menu-item-type-post_type menu-item-object-page menu-item-2784 nav-item\"><a title=\"Accessories\" href=\"https://rsgprofilesheets.com/accessories/\" class=\"dropdown-items\">Accessories</a></li>\n\t</ul>\n<div class=\"dropdown-btn\"><span class=\"fas fa-angle-down\"></span></div></li>\n\t<li itemscope=\"itemscope\" itemtype=\"https://www.schema.org/SiteNavigationElement\" id=\"menu-item-2785\" class=\"menu-item menu-item-type-post_type menu-item-object-page menu-item-2785 nav-item\"><a title=\"Decking Sheet\" href=\"https://rsgprofilesheets.com/decking-sheet/\" class=\"dropdown-items\">Decking Sheet</a></li>\n\t<li itemscope=\"itemscope\" itemtype=\"https://www.schema.org/SiteNavigationElement\" id=\"menu-item-3048\" class=\"menu-item menu-item-type-post_type menu-item-object-page menu-item-3048 nav-item\"><a title=\"Galvanized Plain Sheets\" href=\"https://rsgprofilesheets.com/galvanized-plain-sheets/\" class=\"dropdown-items\">Galvanized Plain Sheets</a></li>\n\t<li itemscope=\"itemscope\" itemtype=\"https://www.schema.org/SiteNavigationElement\" id=\"menu-item-3047\" class=\"menu-item menu-item-type-post_type menu-item-object-page menu-item-3047 nav-item\"><a title=\"C and Z Purlins\" href=\"https://rsgprofilesheets.com/c-and-z-purlins/\" class=\"dropdown-items\">C and Z Purlins</a></li>\n\t<li itemscope=\"itemscope\" itemtype=\"https://www.schema.org/SiteNavigationElement\" id=\"menu-item-3049\" class=\"menu-item menu-item-type-post_type menu-item-object-page menu-item-3049 nav-item\"><a title=\"Crimping Sheet\" href=\"https://rsgprofilesheets.com/crimping-sheet/\" class=\"dropdown-items\">Crimping Sheet</a></li>\n\t<li itemscope=\"itemscope\" itemtype=\"https://www.schema.org/SiteNavigationElement\" id=\"menu-item-2786\" class=\"menu-item menu-item-type-post_type menu-item-object-page menu-item-2786 nav-item\"><a title=\"MS Plate / Channel / Angle\" href=\"https://rsgprofilesheets.com/ms-plate-channel-angle/\" class=\"dropdown-items\">MS Plate / Channel / Angle</a></li>\n\t<li itemscope=\"itemscope\" itemtype=\"https://www.schema.org/SiteNavigationElement\" id=\"menu-item-2787\" class=\"menu-item menu-item-type-post_type menu-item-object-page menu-item-2787 nav-item\"><a title=\"Polycarbonate Sheet\" href=\"https://rsgprofilesheets.com/polycarbonate-sheet/\" class=\"dropdown-items\">Polycarbonate Sheet</a></li>\n\t<li itemscope=\"itemscope\" itemtype=\"https://www.schema.org/SiteNavigationElement\" id=\"menu-item-3413\" class=\"menu-item menu-item-type-post_type menu-item-object-page menu-item-3413 nav-item\"><a title=\"Ms Pipe\" href=\"https://rsgprofilesheets.com/ms-pipe/\" class=\"dropdown-items\">Ms Pipe</a></li>\n</ul>\n<div class=\"dropdown-btn\"><span class=\"fas fa-angle-down\"></span></div></li>\n<li itemscope=\"itemscope\" itemtype=\"https://www.schema.org/SiteNavigationElement\" id=\"menu-item-1502\" class=\"menu-item menu-item-type-post_type menu-item-object-page menu-item-1502 nav-item\"><a title=\"Contact\" href=\"https://rsgprofilesheets.com/contact/\" class=\"nav-links\">Contact</a></li>\n<li itemscope=\"itemscope\" itemtype=\"https://www.schema.org/SiteNavigationElement\" id=\"menu-item-1613\" class=\"menu-item menu-item-type-post_type menu-item-object-page menu-item-1613 nav-item\"><a title=\"Careers\" href=\"https://rsgprofilesheets.com/career/\" class=\"nav-links\">Careers</a></li>\n</ul>                                </div>\n\n                                                            <div class=\"header-action d-none d-md-block\">\n                                    <ul class=\"list-wrap\">\n                                        <li class=\"header-btn\"><a href=\"https://rsgprofilesheets.com/contact/\" class=\"btn\">Get a Quote</a></li>\n                                    </ul>\n                                </div>\n                            \n                        </nav>\n                    </div>\n\n                    <!-- Mobile Menu  -->\n                    <div class=\"mobile-menu\">\n                        <nav class=\"menu-box\">\n                            <div class=\"close-btn\"><i class=\"fas fa-times\"></i></div>\n                            <div class=\"nav-logo\">\n                                \n    <a class=\"main-logo\" href=\"https://rsgprofilesheets.com/\">\n        <img src=\"https://rsgprofilesheets.com/wp-content/uploads/2024/09/rsg-logo.png\" style=\"max-height: 80px\" alt=\"Logo\">\n    </a>\n\n                            </div>\n                            <div class=\"menu-outer\">\n                                <!--Here Menu Will Come Automatically Via Javascript / Same Menu as in Header-->\n                            \n                                    <ul id=\"menu-global-menu\" class=\"navigation\"><li itemscope=\"itemscope\" itemtype=\"https://www.schema.org/SiteNavigationElement\" id=\"menu-item-1495\" class=\"menu-item menu-item-type-post_type menu-item-object-page menu-item-home menu-item-1495 nav-item\"><a title=\"Home\" href=\"https://rsgprofilesheets.com/\" class=\"nav-links\">Home</a></li>\n<li itemscope=\"itemscope\" itemtype=\"https://www.schema.org/SiteNavigationElement\" id=\"menu-item-1494\" class=\"menu-item menu-item-type-post_type menu-item-object-page menu-item-1494 nav-item\"><a title=\"About Us\" href=\"https://rsgprofilesheets.com/about-us-2/\" class=\"nav-links\">About Us</a></li>\n<li itemscope=\"itemscope\" itemtype=\"https://www.schema.org/SiteNavigationElement\" id=\"menu-item-1547\" class=\"menu-item menu-item-type-post_type menu-item-object-page menu-item-has-children dropdown has-dropdown menu-item-1547 nav-item\"><a title=\"Products\" href=\"https://rsgprofilesheets.com/products/\" class=\"nav-links\">Products</a>\n<ul class=\"sub-menu\" role=\"menu\">\n\t<li itemscope=\"itemscope\" itemtype=\"https://www.schema.org/SiteNavigationElement\" id=\"menu-item-2888\" class=\"menu-item menu-item-type-custom menu-item-object-custom menu-item-has-children dropdown has-dropdown menu-item-2888 nav-item\"><a title=\"Colour Coated Roofing Sheet\" href=\"https://rsgprofilesheets.com/colour-coated-roofing-sheets/#\" class=\"dropdown-items\">Colour Coated Roofing Sheet</a>\n\t<ul class=\"sub-menu\" role=\"menu\">\n\t\t<li itemscope=\"itemscope\" itemtype=\"https://www.schema.org/SiteNavigationElement\" id=\"menu-item-2889\" class=\"menu-item menu-item-type-custom menu-item-object-custom menu-item-has-children dropdown has-dropdown menu-item-2889 nav-item\"><a title=\"PPGL\" href=\"https://rsgprofilesheets.com/colour-coated-roofing-sheets/#\" class=\"dropdown-items\">PPGL</a>\n\t\t<ul class=\"sub-menu\" role=\"menu\">\n\t\t\t<li itemscope=\"itemscope\" itemtype=\"https://www.schema.org/SiteNavigationElement\" id=\"menu-item-2565\" class=\"menu-item menu-item-type-post_type menu-item-object-page menu-item-2565 nav-item\"><a title=\"JSW Colouron+\" href=\"https://rsgprofilesheets.com/jsw-colouron/\" class=\"dropdown-items\">JSW Colouron+</a></li>\n\t\t\t<li itemscope=\"itemscope\" itemtype=\"https://www.schema.org/SiteNavigationElement\" id=\"menu-item-2567\" class=\"menu-item menu-item-type-post_type menu-item-object-page menu-item-2567 nav-item\"><a title=\"JSW Silveron+\" href=\"https://rsgprofilesheets.com/jsw-silveron/\" class=\"dropdown-items\">JSW Silveron+</a></li>\n\t\t\t<li itemscope=\"itemscope\" itemtype=\"https://www.schema.org/SiteNavigationElement\" id=\"menu-item-2566\" class=\"menu-item menu-item-type-post_type menu-item-object-page menu-item-2566 nav-item\"><a title=\"JSW Pragati+\" href=\"https://rsgprofilesheets.com/jsw-pragati/\" class=\"dropdown-items\">JSW Pragati+</a></li>\n\t\t\t<li itemscope=\"itemscope\" itemtype=\"https://www.schema.org/SiteNavigationElement\" id=\"menu-item-3085\" class=\"menu-item menu-item-type-post_type menu-item-object-page menu-item-3085 nav-item\"><a title=\"JSW Endura\" href=\"https://rsgprofilesheets.com/jsw-endura/\" class=\"dropdown-items\">JSW Endura</a></li>\n\t\t\t<li itemscope=\"itemscope\" itemtype=\"https://www.schema.org/SiteNavigationElement\" id=\"menu-item-2571\" class=\"menu-item menu-item-type-post_type menu-item-object-page menu-item-2571 nav-item\"><a title=\"Tata Durashine\" href=\"https://rsgprofilesheets.com/tata-durashine/\" class=\"dropdown-items\">Tata Durashine</a></li>\n\t\t\t<li itemscope=\"itemscope\" itemtype=\"https://www.schema.org/SiteNavigationElement\" id=\"menu-item-2564\" class=\"menu-item menu-item-type-post_type menu-item-object-page menu-item-2564 nav-item\"><a title=\"JINDAL India Sabrang\" href=\"https://rsgprofilesheets.com/jindal-sabrang/\" class=\"dropdown-items\">JINDAL India Sabrang</a></li>\n\t\t</ul>\n<div class=\"dropdown-btn\"><span class=\"fas fa-angle-down\"></span></div></li>\n\t\t<li itemscope=\"itemscope\" itemtype=\"https://www.schema.org/SiteNavigationElement\" id=\"menu-item-2890\" class=\"menu-item menu-item-type-custom menu-item-object-custom menu-item-has-children dropdown has-dropdown menu-item-2890 nav-item\"><a title=\"PPGI\" href=\"https://rsgprofilesheets.com/colour-coated-roofing-sheets/#\" class=\"dropdown-items\">PPGI</a>\n\t\t<ul class=\"sub-menu\" role=\"menu\">\n\t\t\t<li itemscope=\"itemscope\" itemtype=\"https://www.schema.org/SiteNavigationElement\" id=\"menu-item-2562\" class=\"menu-item menu-item-type-post_type menu-item-object-page menu-item-2562 nav-item\"><a title=\"Dura Glow\" href=\"https://rsgprofilesheets.com/dura-glow/\" class=\"dropdown-items\">Dura Glow</a></li>\n\t\t\t<li itemscope=\"itemscope\" itemtype=\"https://www.schema.org/SiteNavigationElement\" id=\"menu-item-2558\" class=\"menu-item menu-item-type-post_type menu-item-object-page menu-item-2558 nav-item\"><a title=\"AM/NS\" href=\"https://rsgprofilesheets.com/am-ns/\" class=\"dropdown-items\">AM/NS</a></li>\n\t\t</ul>\n<div class=\"dropdown-btn\"><span class=\"fas fa-angle-down\"></span></div></li>\n\t\t<li itemscope=\"itemscope\" itemtype=\"https://www.schema.org/SiteNavigationElement\" id=\"menu-item-2784\" class=\"menu-item menu-item-type-post_type menu-item-object-page menu-item-2784 nav-item\"><a title=\"Accessories\" href=\"https://rsgprofilesheets.com/accessories/\" class=\"dropdown-items\">Accessories</a></li>\n\t</ul>\n<div class=\"dropdown-btn\"><span class=\"fas fa-angle-down\"></span></div></li>\n\t<li itemscope=\"itemscope\" itemtype=\"https://www.schema.org/SiteNavigationElement\" id=\"menu-item-2785\" class=\"menu-item menu-item-type-post_type menu-item-object-page menu-item-2785 nav-item\"><a title=\"Decking Sheet\" href=\"https://rsgprofilesheets.com/decking-sheet/\" class=\"dropdown-items\">Decking Sheet</a></li>\n\t<li itemscope=\"itemscope\" itemtype=\"https://www.schema.org/SiteNavigationElement\" id=\"menu-item-3048\" class=\"menu-item menu-item-type-post_type menu-item-object-page menu-item-3048 nav-item\"><a title=\"Galvanized Plain Sheets\" href=\"https://rsgprofilesheets.com/galvanized-plain-sheets/\" class=\"dropdown-items\">Galvanized Plain Sheets</a></li>\n\t<li itemscope=\"itemscope\" itemtype=\"https://www.schema.org/SiteNavigationElement\" id=\"menu-item-3047\" class=\"menu-item menu-item-type-post_type menu-item-object-page menu-item-3047 nav-item\"><a title=\"C and Z Purlins\" href=\"https://rsgprofilesheets.com/c-and-z-purlins/\" class=\"dropdown-items\">C and Z Purlins</a></li>\n\t<li itemscope=\"itemscope\" itemtype=\"https://www.schema.org/SiteNavigationElement\" id=\"menu-item-3049\" class=\"menu-item menu-item-type-post_type menu-item-object-page menu-item-3049 nav-item\"><a title=\"Crimping Sheet\" href=\"https://rsgprofilesheets.com/crimping-sheet/\" class=\"dropdown-items\">Crimping Sheet</a></li>\n\t<li itemscope=\"itemscope\" itemtype=\"https://www.schema.org/SiteNavigationElement\" id=\"menu-item-2786\" class=\"menu-item menu-item-type-post_type menu-item-object-page menu-item-2786 nav-item\"><a title=\"MS Plate / Channel / Angle\" href=\"https://rsgprofilesheets.com/ms-plate-channel-angle/\" class=\"dropdown-items\">MS Plate / Channel / Angle</a></li>\n\t<li itemscope=\"itemscope\" itemtype=\"https://www.schema.org/SiteNavigationElement\" id=\"menu-item-2787\" class=\"menu-item menu-item-type-post_type menu-item-object-page menu-item-2787 nav-item\"><a title=\"Polycarbonate Sheet\" href=\"https://rsgprofilesheets.com/polycarbonate-sheet/\" class=\"dropdown-items\">Polycarbonate Sheet</a></li>\n\t<li itemscope=\"itemscope\" itemtype=\"https://www.schema.org/SiteNavigationElement\" id=\"menu-item-3413\" class=\"menu-item menu-item-type-post_type menu-item-object-page menu-item-3413 nav-item\"><a title=\"Ms Pipe\" href=\"https://rsgprofilesheets.com/ms-pipe/\" class=\"dropdown-items\">Ms Pipe</a></li>\n</ul>\n<div class=\"dropdown-btn\"><span class=\"fas fa-angle-down\"></span></div></li>\n<li itemscope=\"itemscope\" itemtype=\"https://www.schema.org/SiteNavigationElement\" id=\"menu-item-1502\" class=\"menu-item menu-item-type-post_type menu-item-object-page menu-item-1502 nav-item\"><a title=\"Contact\" href=\"https://rsgprofilesheets.com/contact/\" class=\"nav-links\">Contact</a></li>\n<li itemscope=\"itemscope\" itemtype=\"https://www.schema.org/SiteNavigationElement\" id=\"menu-item-1613\" class=\"menu-item menu-item-type-post_type menu-item-object-page menu-item-1613 nav-item\"><a title=\"Careers\" href=\"https://rsgprofilesheets.com/career/\" class=\"nav-links\">Careers</a></li>\n</ul>                                </div>\n\n                                                            <div class=\"social-links\">\n                                    \n    <ul class=\"clearfix\">\n                <li class=\"facebook\">\n            <a href=\"https://rsgprofilesheets.com/colour-coated-roofing-sheets/#\"><i class=\"fab fa-facebook-f\"></i></a>\n        </li>\n        \n                <li class=\"twitter\">\n            <a href=\"https://rsgprofilesheets.com/colour-coated-roofing-sheets/#\"><i class=\"fab fa-twitter\"></i></a>\n        </li>\n        \n                <li class=\"instagram\">\n            <a href=\"https://rsgprofilesheets.com/colour-coated-roofing-sheets/#\"><i class=\"fab fa-instagram\"></i></a>\n        </li>\n        \n                <li class=\"linkedin\">\n            <a href=\"https://rsgprofilesheets.com/colour-coated-roofing-sheets/#\"><i class=\"fab fa-linkedin-in\"></i></a>\n        </li>\n        \n                <li class=\"telegram\">\n            <a href=\"https://rsgprofilesheets.com/colour-coated-roofing-sheets/#\"><i class=\"fab fa-telegram-plane\"></i></a>\n        </li>\n            </ul>\n\n                                </div>\n                            \n                        </nav>\n                    </div>\n                    <div class=\"menu-backdrop\"></div>\n                    <!-- End Mobile Menu -->\n\n                </div>\n            </div>\n        </div>\n    </div>\n</header>\n<!-- header-area-end -->\n    <!-- main-area -->\n    <main class=\"main-area\">\n\n        \n                    <!-- breadcrumb-area -->\n            <section class=\"breadcrumb-area breadcrumb-bg \" data-background=\"https://rsgprofilesheets.com/wp-content/uploads/2024/09/Untitled-design-18.png\" style=\"background-image: url(&quot;https://rsgprofilesheets.com/wp-content/uploads/2024/09/Untitled-design-18.png&quot;);\">\n                <div class=\"container\">\n                    <div class=\"row\">\n                        <div class=\"col-lg-12\">\n                            <div class=\"breadcrumb-content\">\n                                <h2 class=\"title\">Page not Found</h2>\n\n                                                                    <nav aria-label=\"breadcrumb\" class=\"breadcrumb\">\n                                        <!-- Breadcrumb NavXT 7.5.0 -->\n<span property=\"itemListElement\" typeof=\"ListItem\"><a property=\"item\" typeof=\"WebPage\" title=\"Go to RSG.\" href=\"https://rsgprofilesheets.com/\" class=\"home\"><span property=\"name\">RSG</span></a></span> &gt; <span property=\"itemListElement\" typeof=\"ListItem\"><a property=\"item\" typeof=\"WebPage\" title=\"Go to 404.\" href=\"https://rsgprofilesheets.com/colour-coated-roofing-sheets/\" class=\"404 current-item\" aria-current=\"page\"><span property=\"name\">404</span></a></span>                                    </nav>\n                                \n                            </div>\n                        </div>\n                    </div>\n                </div>\n            </section>\n            <!-- breadcrumb-area-end -->\n        \n\n\n\n<!-- error-area -->\n<section class=\"error-area\">\n    <div class=\"container\">\n        <div class=\"row justify-content-center\">\n            <div class=\"col-xl-7 col-lg-9 col-md-10\">\n                <div class=\"error-content text-center\">\n                    <h2 class=\"error-text\">404</h2>\n                    <h5 class=\"content\">Sorry, the page you are looking for could not be found</h5>\n                    <a href=\"https://rsgprofilesheets.com/\" class=\"btn\">\n                        Back to home                        <span></span>\n                    </a>\n                </div>\n            </div>\n        </div>\n    </div>\n</section>\n<!-- error-area-end -->\n\n\n\t\t<footer itemtype=\"https://schema.org/WPFooter\" itemscope=\"itemscope\" id=\"colophon\" role=\"contentinfo\">\n\t\t\t<div class=\"footer-width-fixer\">\t\t<div data-elementor-type=\"wp-post\" data-elementor-id=\"1097\" class=\"elementor elementor-1097\" data-elementor-post-type=\"elementor-hf\">\n\t\t\t\t\t\t<section class=\"elementor-section elementor-top-section elementor-element elementor-element-ddf657a elementor-section-boxed elementor-section-height-default elementor-section-height-default\" data-id=\"ddf657a\" data-element_type=\"section\" data-settings=\"{&quot;background_background&quot;:&quot;classic&quot;}\">\n\t\t\t\t\t\t<div class=\"elementor-container elementor-column-gap-default\">\n\t\t\t\t\t<div class=\"elementor-column elementor-col-100 elementor-top-column elementor-element elementor-element-a645e4b\" data-id=\"a645e4b\" data-element_type=\"column\">\n\t\t\t<div class=\"elementor-widget-wrap elementor-element-populated\">\n\t\t\t\t\t\t<section class=\"elementor-section elementor-inner-section elementor-element elementor-element-f56cfa5 elementor-section-full_width elementor-section-height-default elementor-section-height-default\" data-id=\"f56cfa5\" data-element_type=\"section\">\n\t\t\t\t\t\t<div class=\"elementor-container elementor-column-gap-no\">\n\t\t\t\t\t<div class=\"elementor-column elementor-col-25 elementor-inner-column elementor-element elementor-element-fa0d060\" data-id=\"fa0d060\" data-element_type=\"column\">\n\t\t\t<div class=\"elementor-widget-wrap elementor-element-populated\">\n\t\t\t\t\t\t<div class=\"elementor-element elementor-element-f82feb4 elementor-widget elementor-widget-heading\" data-id=\"f82feb4\" data-element_type=\"widget\" data-widget_type=\"heading.default\">\n\t\t\t\t<div class=\"elementor-widget-container\">\n\t\t\t\t\t<h2 class=\"elementor-heading-title elementor-size-default\">About Us</h2>\t\t\t\t</div>\n\t\t\t\t</div>\n\t\t\t\t<div class=\"elementor-element elementor-element-1fc40e3 elementor-widget elementor-widget-heading\" data-id=\"1fc40e3\" data-element_type=\"widget\" data-widget_type=\"heading.default\">\n\t\t\t\t<div class=\"elementor-widget-container\">\n\t\t\t\t\t<h2 class=\"elementor-heading-title elementor-size-default\">RSG Profile Manufacturing Private Limited is one of the top makers of roofing sheets with a selection of profiles to meet customer needs. o satisfy the various demands of the industry.</h2>\t\t\t\t</div>\n\t\t\t\t</div>\n\t\t\t\t\t</div>\n\t\t</div>\n\t\t\t\t<div class=\"elementor-column elementor-col-25 elementor-inner-column elementor-element elementor-element-e173bcd\" data-id=\"e173bcd\" data-element_type=\"column\">\n\t\t\t<div class=\"elementor-widget-wrap elementor-element-populated\">\n\t\t\t\t\t\t<div class=\"elementor-element elementor-element-1716992 elementor-widget elementor-widget-heading\" data-id=\"1716992\" data-element_type=\"widget\" data-widget_type=\"heading.default\">\n\t\t\t\t<div class=\"elementor-widget-container\">\n\t\t\t\t\t<h2 class=\"elementor-heading-title elementor-size-default\">Our Products</h2>\t\t\t\t</div>\n\t\t\t\t</div>\n\t\t\t\t<div class=\"elementor-element elementor-element-fa35b81 elementor-icon-list--layout-traditional elementor-list-item-link-full_width elementor-widget elementor-widget-icon-list\" data-id=\"fa35b81\" data-element_type=\"widget\" data-widget_type=\"icon-list.default\">\n\t\t\t\t<div class=\"elementor-widget-container\">\n\t\t\t\t\t\t\t<ul class=\"elementor-icon-list-items\">\n\t\t\t\t\t\t\t<li class=\"elementor-icon-list-item\">\n\t\t\t\t\t\t\t\t\t\t\t<a href=\"https://rsgprofilesheets.com/accessories/\">\n\n\t\t\t\t\t\t\t\t\t\t\t\t<span class=\"elementor-icon-list-icon\">\n\t\t\t\t\t\t\t<svg aria-hidden=\"true\" class=\"e-font-icon-svg e-fas-arrow-circle-right\" viewBox=\"0 0 512 512\" xmlns=\"http://www.w3.org/2000/svg\"><path d=\"M256 8c137 0 248 111 248 248S393 504 256 504 8 393 8 256 119 8 256 8zm-28.9 143.6l75.5 72.4H120c-13.3 0-24 10.7-24 24v16c0 13.3 10.7 24 24 24h182.6l-75.5 72.4c-9.7 9.3-9.9 24.8-.4 34.3l11 10.9c9.4 9.4 24.6 9.4 33.9 0L404.3 273c9.4-9.4 9.4-24.6 0-33.9L271.6 106.3c-9.4-9.4-24.6-9.4-33.9 0l-11 10.9c-9.5 9.6-9.3 25.1.4 34.4z\"></path></svg>\t\t\t\t\t\t</span>\n\t\t\t\t\t\t\t\t\t\t<span class=\"elementor-icon-list-text\">Color Coated Roofing Sheet</span>\n\t\t\t\t\t\t\t\t\t\t\t</a>\n\t\t\t\t\t\t\t\t\t</li>\n\t\t\t\t\t\t\t\t<li class=\"elementor-icon-list-item\">\n\t\t\t\t\t\t\t\t\t\t\t<a href=\"https://rsgprofilesheets.com/rsg-category/ms-pipe/\">\n\n\t\t\t\t\t\t\t\t\t\t\t\t<span class=\"elementor-icon-list-icon\">\n\t\t\t\t\t\t\t<svg aria-hidden=\"true\" class=\"e-font-icon-svg e-fas-arrow-circle-right\" viewBox=\"0 0 512 512\" xmlns=\"http://www.w3.org/2000/svg\"><path d=\"M256 8c137 0 248 111 248 248S393 504 256 504 8 393 8 256 119 8 256 8zm-28.9 143.6l75.5 72.4H120c-13.3 0-24 10.7-24 24v16c0 13.3 10.7 24 24 24h182.6l-75.5 72.4c-9.7 9.3-9.9 24.8-.4 34.3l11 10.9c9.4 9.4 24.6 9.4 33.9 0L404.3 273c9.4-9.4 9.4-24.6 0-33.9L271.6 106.3c-9.4-9.4-24.6-9.4-33.9 0l-11 10.9c-9.5 9.6-9.3 25.1.4 34.4z\"></path></svg>\t\t\t\t\t\t</span>\n\t\t\t\t\t\t\t\t\t\t<span class=\"elementor-icon-list-text\">Ms Pipe</span>\n\t\t\t\t\t\t\t\t\t\t\t</a>\n\t\t\t\t\t\t\t\t\t</li>\n\t\t\t\t\t\t\t\t<li class=\"elementor-icon-list-item\">\n\t\t\t\t\t\t\t\t\t\t\t<a href=\"https://rsgprofilesheets.com/decking-sheet/\">\n\n\t\t\t\t\t\t\t\t\t\t\t\t<span class=\"elementor-icon-list-icon\">\n\t\t\t\t\t\t\t<svg aria-hidden=\"true\" class=\"e-font-icon-svg e-fas-arrow-circle-right\" viewBox=\"0 0 512 512\" xmlns=\"http://www.w3.org/2000/svg\"><path d=\"M256 8c137 0 248 111 248 248S393 504 256 504 8 393 8 256 119 8 256 8zm-28.9 143.6l75.5 72.4H120c-13.3 0-24 10.7-24 24v16c0 13.3 10.7 24 24 24h182.6l-75.5 72.4c-9.7 9.3-9.9 24.8-.4 34.3l11 10.9c9.4 9.4 24.6 9.4 33.9 0L404.3 273c9.4-9.4 9.4-24.6 0-33.9L271.6 106.3c-9.4-9.4-24.6-9.4-33.9 0l-11 10.9c-9.5 9.6-9.3 25.1.4 34.4z\"></path></svg>\t\t\t\t\t\t</span>\n\t\t\t\t\t\t\t\t\t\t<span class=\"elementor-icon-list-text\">Decking Sheets</span>\n\t\t\t\t\t\t\t\t\t\t\t</a>\n\t\t\t\t\t\t\t\t\t</li>\n\t\t\t\t\t\t\t\t<li class=\"elementor-icon-list-item\">\n\t\t\t\t\t\t\t\t\t\t\t<a href=\"https://rsgprofilesheets.com/galvanized-plain-sheets/\">\n\n\t\t\t\t\t\t\t\t\t\t\t\t<span class=\"elementor-icon-list-icon\">\n\t\t\t\t\t\t\t<svg aria-hidden=\"true\" class=\"e-font-icon-svg e-fas-arrow-circle-right\" viewBox=\"0 0 512 512\" xmlns=\"http://www.w3.org/2000/svg\"><path d=\"M256 8c137 0 248 111 248 248S393 504 256 504 8 393 8 256 119 8 256 8zm-28.9 143.6l75.5 72.4H120c-13.3 0-24 10.7-24 24v16c0 13.3 10.7 24 24 24h182.6l-75.5 72.4c-9.7 9.3-9.9 24.8-.4 34.3l11 10.9c9.4 9.4 24.6 9.4 33.9 0L404.3 273c9.4-9.4 9.4-24.6 0-33.9L271.6 106.3c-9.4-9.4-24.6-9.4-33.9 0l-11 10.9c-9.5 9.6-9.3 25.1.4 34.4z\"></path></svg>\t\t\t\t\t\t</span>\n\t\t\t\t\t\t\t\t\t\t<span class=\"elementor-icon-list-text\">Galvanized Plain Sheets</span>\n\t\t\t\t\t\t\t\t\t\t\t</a>\n\t\t\t\t\t\t\t\t\t</li>\n\t\t\t\t\t\t\t\t<li class=\"elementor-icon-list-item\">\n\t\t\t\t\t\t\t\t\t\t\t<a href=\"https://rsgprofilesheets.com/crimping-sheet/\">\n\n\t\t\t\t\t\t\t\t\t\t\t\t<span class=\"elementor-icon-list-icon\">\n\t\t\t\t\t\t\t<svg aria-hidden=\"true\" class=\"e-font-icon-svg e-fas-arrow-circle-right\" viewBox=\"0 0 512 512\" xmlns=\"http://www.w3.org/2000/svg\"><path d=\"M256 8c137 0 248 111 248 248S393 504 256 504 8 393 8 256 119 8 256 8zm-28.9 143.6l75.5 72.4H120c-13.3 0-24 10.7-24 24v16c0 13.3 10.7 24 24 24h182.6l-75.5 72.4c-9.7 9.3-9.9 24.8-.4 34.3l11 10.9c9.4 9.4 24.6 9.4 33.9 0L404.3 273c9.4-9.4 9.4-24.6 0-33.9L271.6 106.3c-9.4-9.4-24.6-9.4-33.9 0l-11 10.9c-9.5 9.6-9.3 25.1.4 34.4z\"></path></svg>\t\t\t\t\t\t</span>\n\t\t\t\t\t\t\t\t\t\t<span class=\"elementor-icon-list-text\">Crimping Sheet</span>\n\t\t\t\t\t\t\t\t\t\t\t</a>\n\t\t\t\t\t\t\t\t\t</li>\n\t\t\t\t\t\t\t\t<li class=\"elementor-icon-list-item\">\n\t\t\t\t\t\t\t\t\t\t\t<a href=\"https://rsgprofilesheets.com/ms-plate-channel-angle/\">\n\n\t\t\t\t\t\t\t\t\t\t\t\t<span class=\"elementor-icon-list-icon\">\n\t\t\t\t\t\t\t<svg aria-hidden=\"true\" class=\"e-font-icon-svg e-fas-arrow-circle-right\" viewBox=\"0 0 512 512\" xmlns=\"http://www.w3.org/2000/svg\"><path d=\"M256 8c137 0 248 111 248 248S393 504 256 504 8 393 8 256 119 8 256 8zm-28.9 143.6l75.5 72.4H120c-13.3 0-24 10.7-24 24v16c0 13.3 10.7 24 24 24h182.6l-75.5 72.4c-9.7 9.3-9.9 24.8-.4 34.3l11 10.9c9.4 9.4 24.6 9.4 33.9 0L404.3 273c9.4-9.4 9.4-24.6 0-33.9L271.6 106.3c-9.4-9.4-24.6-9.4-33.9 0l-11 10.9c-9.5 9.6-9.3 25.1.4 34.4z\"></path></svg>\t\t\t\t\t\t</span>\n\t\t\t\t\t\t\t\t\t\t<span class=\"elementor-icon-list-text\">MS Plate</span>\n\t\t\t\t\t\t\t\t\t\t\t</a>\n\t\t\t\t\t\t\t\t\t</li>\n\t\t\t\t\t\t\t\t<li class=\"elementor-icon-list-item\">\n\t\t\t\t\t\t\t\t\t\t\t<a href=\"https://rsgprofilesheets.com/polycarbonate-sheet/\">\n\n\t\t\t\t\t\t\t\t\t\t\t\t<span class=\"elementor-icon-list-icon\">\n\t\t\t\t\t\t\t<svg aria-hidden=\"true\" class=\"e-font-icon-svg e-fas-arrow-circle-right\" viewBox=\"0 0 512 512\" xmlns=\"http://www.w3.org/2000/svg\"><path d=\"M256 8c137 0 248 111 248 248S393 504 256 504 8 393 8 256 119 8 256 8zm-28.9 143.6l75.5 72.4H120c-13.3 0-24 10.7-24 24v16c0 13.3 10.7 24 24 24h182.6l-75.5 72.4c-9.7 9.3-9.9 24.8-.4 34.3l11 10.9c9.4 9.4 24.6 9.4 33.9 0L404.3 273c9.4-9.4 9.4-24.6 0-33.9L271.6 106.3c-9.4-9.4-24.6-9.4-33.9 0l-11 10.9c-9.5 9.6-9.3 25.1.4 34.4z\"></path></svg>\t\t\t\t\t\t</span>\n\t\t\t\t\t\t\t\t\t\t<span class=\"elementor-icon-list-text\">Polycarbonate Sheet</span>\n\t\t\t\t\t\t\t\t\t\t\t</a>\n\t\t\t\t\t\t\t\t\t</li>\n\t\t\t\t\t\t\t\t<li class=\"elementor-icon-list-item\">\n\t\t\t\t\t\t\t\t\t\t\t<a href=\"https://rsgprofilesheets.com/purlins/\">\n\n\t\t\t\t\t\t\t\t\t\t\t\t<span class=\"elementor-icon-list-icon\">\n\t\t\t\t\t\t\t<svg aria-hidden=\"true\" class=\"e-font-icon-svg e-fas-arrow-circle-right\" viewBox=\"0 0 512 512\" xmlns=\"http://www.w3.org/2000/svg\"><path d=\"M256 8c137 0 248 111 248 248S393 504 256 504 8 393 8 256 119 8 256 8zm-28.9 143.6l75.5 72.4H120c-13.3 0-24 10.7-24 24v16c0 13.3 10.7 24 24 24h182.6l-75.5 72.4c-9.7 9.3-9.9 24.8-.4 34.3l11 10.9c9.4 9.4 24.6 9.4 33.9 0L404.3 273c9.4-9.4 9.4-24.6 0-33.9L271.6 106.3c-9.4-9.4-24.6-9.4-33.9 0l-11 10.9c-9.5 9.6-9.3 25.1.4 34.4z\"></path></svg>\t\t\t\t\t\t</span>\n\t\t\t\t\t\t\t\t\t\t<span class=\"elementor-icon-list-text\">Purlins</span>\n\t\t\t\t\t\t\t\t\t\t\t</a>\n\t\t\t\t\t\t\t\t\t</li>\n\t\t\t\t\t\t</ul>\n\t\t\t\t\t\t</div>\n\t\t\t\t</div>\n\t\t\t\t\t</div>\n\t\t</div>\n\t\t\t\t<div class=\"elementor-column elementor-col-25 elementor-inner-column elementor-element elementor-element-caf6580\" data-id=\"caf6580\" data-element_type=\"column\">\n\t\t\t<div class=\"elementor-widget-wrap elementor-element-populated\">\n\t\t\t\t\t\t<div class=\"elementor-element elementor-element-771a140 elementor-widget elementor-widget-heading\" data-id=\"771a140\" data-element_type=\"widget\" data-widget_type=\"heading.default\">\n\t\t\t\t<div class=\"elementor-widget-container\">\n\t\t\t\t\t<h2 class=\"elementor-heading-title elementor-size-default\">Quick Links</h2>\t\t\t\t</div>\n\t\t\t\t</div>\n\t\t\t\t<div class=\"elementor-element elementor-element-a070fa3 elementor-icon-list--layout-traditional elementor-list-item-link-full_width elementor-widget elementor-widget-icon-list\" data-id=\"a070fa3\" data-element_type=\"widget\" data-widget_type=\"icon-list.default\">\n\t\t\t\t<div class=\"elementor-widget-container\">\n\t\t\t\t\t\t\t<ul class=\"elementor-icon-list-items\">\n\t\t\t\t\t\t\t<li class=\"elementor-icon-list-item\">\n\t\t\t\t\t\t\t\t\t\t\t<a href=\"https://rsgprofilesheets.com/\">\n\n\t\t\t\t\t\t\t\t\t\t\t\t<span class=\"elementor-icon-list-icon\">\n\t\t\t\t\t\t\t<svg aria-hidden=\"true\" class=\"e-font-icon-svg e-fas-arrow-circle-right\" viewBox=\"0 0 512 512\" xmlns=\"http://www.w3.org/2000/svg\"><path d=\"M256 8c137 0 248 111 248 248S393 504 256 504 8 393 8 256 119 8 256 8zm-28.9 143.6l75.5 72.4H120c-13.3 0-24 10.7-24 24v16c0 13.3 10.7 24 24 24h182.6l-75.5 72.4c-9.7 9.3-9.9 24.8-.4 34.3l11 10.9c9.4 9.4 24.6 9.4 33.9 0L404.3 273c9.4-9.4 9.4-24.6 0-33.9L271.6 106.3c-9.4-9.4-24.6-9.4-33.9 0l-11 10.9c-9.5 9.6-9.3 25.1.4 34.4z\"></path></svg>\t\t\t\t\t\t</span>\n\t\t\t\t\t\t\t\t\t\t<span class=\"elementor-icon-list-text\">Home</span>\n\t\t\t\t\t\t\t\t\t\t\t</a>\n\t\t\t\t\t\t\t\t\t</li>\n\t\t\t\t\t\t\t\t<li class=\"elementor-icon-list-item\">\n\t\t\t\t\t\t\t\t\t\t\t<a href=\"https://rsgprofilesheets.com/about-us-2/\">\n\n\t\t\t\t\t\t\t\t\t\t\t\t<span class=\"elementor-icon-list-icon\">\n\t\t\t\t\t\t\t<svg aria-hidden=\"true\" class=\"e-font-icon-svg e-fas-arrow-circle-right\" viewBox=\"0 0 512 512\" xmlns=\"http://www.w3.org/2000/svg\"><path d=\"M256 8c137 0 248 111 248 248S393 504 256 504 8 393 8 256 119 8 256 8zm-28.9 143.6l75.5 72.4H120c-13.3 0-24 10.7-24 24v16c0 13.3 10.7 24 24 24h182.6l-75.5 72.4c-9.7 9.3-9.9 24.8-.4 34.3l11 10.9c9.4 9.4 24.6 9.4 33.9 0L404.3 273c9.4-9.4 9.4-24.6 0-33.9L271.6 106.3c-9.4-9.4-24.6-9.4-33.9 0l-11 10.9c-9.5 9.6-9.3 25.1.4 34.4z\"></path></svg>\t\t\t\t\t\t</span>\n\t\t\t\t\t\t\t\t\t\t<span class=\"elementor-icon-list-text\">About Us</span>\n\t\t\t\t\t\t\t\t\t\t\t</a>\n\t\t\t\t\t\t\t\t\t</li>\n\t\t\t\t\t\t\t\t<li class=\"elementor-icon-list-item\">\n\t\t\t\t\t\t\t\t\t\t\t<a href=\"https://rsgprofilesheets.com/durga-glow/\">\n\n\t\t\t\t\t\t\t\t\t\t\t\t<span class=\"elementor-icon-list-icon\">\n\t\t\t\t\t\t\t<svg aria-hidden=\"true\" class=\"e-font-icon-svg e-fas-arrow-circle-right\" viewBox=\"0 0 512 512\" xmlns=\"http://www.w3.org/2000/svg\"><path d=\"M256 8c137 0 248 111 248 248S393 504 256 504 8 393 8 256 119 8 256 8zm-28.9 143.6l75.5 72.4H120c-13.3 0-24 10.7-24 24v16c0 13.3 10.7 24 24 24h182.6l-75.5 72.4c-9.7 9.3-9.9 24.8-.4 34.3l11 10.9c9.4 9.4 24.6 9.4 33.9 0L404.3 273c9.4-9.4 9.4-24.6 0-33.9L271.6 106.3c-9.4-9.4-24.6-9.4-33.9 0l-11 10.9c-9.5 9.6-9.3 25.1.4 34.4z\"></path></svg>\t\t\t\t\t\t</span>\n\t\t\t\t\t\t\t\t\t\t<span class=\"elementor-icon-list-text\">Products</span>\n\t\t\t\t\t\t\t\t\t\t\t</a>\n\t\t\t\t\t\t\t\t\t</li>\n\t\t\t\t\t\t\t\t<li class=\"elementor-icon-list-item\">\n\t\t\t\t\t\t\t\t\t\t\t<a href=\"https://rsgprofilesheets.com/contact/\">\n\n\t\t\t\t\t\t\t\t\t\t\t\t<span class=\"elementor-icon-list-icon\">\n\t\t\t\t\t\t\t<svg aria-hidden=\"true\" class=\"e-font-icon-svg e-fas-arrow-circle-right\" viewBox=\"0 0 512 512\" xmlns=\"http://www.w3.org/2000/svg\"><path d=\"M256 8c137 0 248 111 248 248S393 504 256 504 8 393 8 256 119 8 256 8zm-28.9 143.6l75.5 72.4H120c-13.3 0-24 10.7-24 24v16c0 13.3 10.7 24 24 24h182.6l-75.5 72.4c-9.7 9.3-9.9 24.8-.4 34.3l11 10.9c9.4 9.4 24.6 9.4 33.9 0L404.3 273c9.4-9.4 9.4-24.6 0-33.9L271.6 106.3c-9.4-9.4-24.6-9.4-33.9 0l-11 10.9c-9.5 9.6-9.3 25.1.4 34.4z\"></path></svg>\t\t\t\t\t\t</span>\n\t\t\t\t\t\t\t\t\t\t<span class=\"elementor-icon-list-text\">Contact Us</span>\n\t\t\t\t\t\t\t\t\t\t\t</a>\n\t\t\t\t\t\t\t\t\t</li>\n\t\t\t\t\t\t</ul>\n\t\t\t\t\t\t</div>\n\t\t\t\t</div>\n\t\t\t\t\t</div>\n\t\t</div>\n\t\t\t\t<div class=\"elementor-column elementor-col-25 elementor-inner-column elementor-element elementor-element-993f5c2\" data-id=\"993f5c2\" data-element_type=\"column\">\n\t\t\t<div class=\"elementor-widget-wrap elementor-element-populated\">\n\t\t\t\t\t\t<div class=\"elementor-element elementor-element-b489b53 elementor-widget elementor-widget-image\" data-id=\"b489b53\" data-element_type=\"widget\" data-widget_type=\"image.default\">\n\t\t\t\t<div class=\"elementor-widget-container\">\n\t\t\t\t\t\t\t\t\t\t\t\t\t\t\t<img width=\"190\" height=\"141\" src=\"https://rsgprofilesheets.com/wp-content/uploads/2024/09/rsg-logo.png\" class=\"attachment-full size-full wp-image-1238\" alt=\"\">\t\t\t\t\t\t\t\t\t\t\t\t\t\t\t</div>\n\t\t\t\t</div>\n\t\t\t\t\t</div>\n\t\t</div>\n\t\t\t\t\t</div>\n\t\t</section>\n\t\t\t\t\t</div>\n\t\t</div>\n\t\t\t\t\t</div>\n\t\t</section>\n\t\t\t\t</div>\n\t\t</div>\t\t</footer>\n\t<!-- #page -->\n\n\t\t\t\n\t\t\t<link rel=\"stylesheet\" id=\"widget-icon-list-css\" href=\"https://rsgprofilesheets.com/wp-content/plugins/elementor/assets/css/widget-icon-list.min.css?ver=3.33.5\" type=\"text/css\" media=\"all\">\n\n\n\n\n\n\n\n\n\n\n\n\n\n\n\n\n\n\n\n\n\n\n\n\n\n\n\n\n\n\n\n\n\n\n\n\n\n\n \n</main><div class=\"cb-cursor\" style=\"transform: translate3d(-1920px, -993px, 0px);\"><div class=\"cb-cursor-text\"></div></div><span id=\"elementor-device-mode\" class=\"elementor-screen-only\"></span><svg style=\"display: none;\" class=\"e-font-icon-svg-symbols\"></svg></body></html>","links":["tel:+91 99185 22988","mailto:shivam.gupta09@gmail.com","https://rsgprofilesheets.com/colour-coated-roofing-sheets/#","https://www.linkedin.com/company/rsg-profile-manufacturing-private-limited/","https://rsgprofilesheets.com/","https://rsgprofilesheets.com/about-us-2/","https://rsgprofilesheets.com/products/","https://rsgprofilesheets.com/jsw-colouron/","https://rsgprofilesheets.com/jsw-silveron/","https://rsgprofilesheets.com/jsw-pragati/","https://rsgprofilesheets.com/jsw-endura/","https://rsgprofilesheets.com/tata-durashine/","https://rsgprofilesheets.com/jindal-sabrang/","https://rsgprofilesheets.com/dura-glow/","https://rsgprofilesheets.com/am-ns/","https://rsgprofilesheets.com/accessories/","https://rsgprofilesheets.com/decking-sheet/","https://rsgprofilesheets.com/galvanized-plain-sheets/","https://rsgprofilesheets.com/c-and-z-purlins/","https://rsgprofilesheets.com/crimping-sheet/","https://rsgprofilesheets.com/ms-plate-channel-angle/","https://rsgprofilesheets.com/polycarbonate-sheet/","https://rsgprofilesheets.com/ms-pipe/","https://rsgprofilesheets.com/contact/","https://rsgprofilesheets.com/career/","https://rsgprofilesheets.com/colour-coated-roofing-sheets/","https://rsgprofilesheets.com/rsg-category/ms-pipe/","https://rsgprofilesheets.com/purlins/","https://rsgprofilesheets.com/durga-glow/"]}